[
    {
        "user_id": "412516621526",
        "verify": false,
        "first_name": "Deneme",
        "last_name": null,
        "try": 3
    },
    {
        "user_id": "412515621526",
        "verify": true,
        "first_name": "Dnm",
        "last_name": null,
        "try": 3
    },
    {
        "user_id": "412516241526",
        "verify": true,
        "first_name": "Test",
        "last_name": null,
        "try": 9996,
        "card-balance": 50,
        "card-cost": 2.25
    },
    {
        "user_id": "412516121526",
        "verify": true,
        "first_name": "FTest",
        "last_name": "Test",
        "try": 2,
        "card-balance": 50,
        "card-cost": 2.25
    },
    {
        "user_id": "412516215226",
        "verify": true,
        "first_name": "Test",
        "last_name": "Test",
        "try": 3,
        "card-balance": 50,
        "card-cost": 2.25
    }
]